swarmauri_certservice_scep/ScepCertService.py
swarmauri_certservice_scep/__init__.py
swarmauri_certservice_scep-0.8.0.dev4.dist-info/LICENSE
swarmauri_certservice_scep-0.8.0.dev4.dist-info/METADATA
swarmauri_certservice_scep-0.8.0.dev4.dist-info/WHEEL
swarmauri_certservice_scep-0.8.0.dev4.dist-info/entry_points.txt
swarmauri_certservice_scep-0.8.0.dev4.dist-info/RECORD
