Metadata-Version: 2.3
Name: swarmauri_certservice_scep
Version: 0.8.0.dev4
Summary: Swarmauri SCEP Certificate Service
License: Apache-2.0
Author: Jacob Stewart
Author-email: jacob@swarmauri.com
Requires-Python: >=3.10,<3.13
Classifier: License :: OSI Approved :: Apache Software License
Classifier: Programming Language :: Python :: 3.10
Classifier: Programming Language :: Python :: 3.11
Classifier: Programming Language :: Python :: 3.12
Provides-Extra: httpx
Requires-Dist: cryptography (>=41.0.0)
Requires-Dist: httpx (>=0.27.0) ; extra == "httpx"
Requires-Dist: requests (>=2.32.3)
Requires-Dist: swarmauri_base
Requires-Dist: swarmauri_core
